sharkpress_word_counter-1.0.0.dist-info/licenses/LICENSE
url_word_counter/__init__.py
url_word_counter/__main__.py
url_word_counter/core.py
sharkpress_word_counter-1.0.0.dist-info/METADATA
sharkpress_word_counter-1.0.0.dist-info/WHEEL
sharkpress_word_counter-1.0.0.dist-info/entry_points.txt
sharkpress_word_counter-1.0.0.dist-info/top_level.txt
sharkpress_word_counter-1.0.0.dist-info/RECORD
