Metadata-Version: 2.4
Name: sharkpress-word-counter
Version: 1.0.0
Summary: A tool to count words in the main content of web pages, ignoring cookie banners and other non-content elements.
Home-page: https://github.com/sharkpress/url-word-counter
Author: Wiktor Jachec
Author-email: hello@sharkpress.agency
Project-URL: Bug Reports, https://github.com/sharkpress/url-word-counter/issues
Project-URL: Source, https://github.com/sharkpress/url-word-counter
Classifier: Programming Language :: Python :: 3
Classifier: License :: OSI Approved :: MIT License
Classifier: Operating System :: OS Independent
Requires-Python: >=3.8
License-File: LICENSE
Requires-Dist: selenium>=4.0.0
Requires-Dist: webdriver-manager>=4.0.0
Requires-Dist: beautifulsoup4>=4.12.0
Dynamic: author
Dynamic: author-email
Dynamic: classifier
Dynamic: description
Dynamic: description-content-type
Dynamic: home-page
Dynamic: license-file
Dynamic: project-url
Dynamic: requires-dist
Dynamic: requires-python
Dynamic: summary
